voskcli/__main__.py
voskcli/transcribe.py
vosk_cli-0.1.dist-info/LICENSE
vosk_cli-0.1.dist-info/METADATA
vosk_cli-0.1.dist-info/WHEEL
vosk_cli-0.1.dist-info/entry_points.txt
vosk_cli-0.1.dist-info/top_level.txt
vosk_cli-0.1.dist-info/RECORD
